{"name":"Escolher um calçado na seção outlet com valor abaixo de R$150,00","id":"escolher-um-calçado-na-seção-outlet-com-valor-abaixo-de-r$150,00:Escolher um calçado na seção outlet com valor abaixo de R$150,00","testSteps":[{"number":1,"description":"Given estou na pagina inicial netShoes \"\u003curl\u003e\"","duration":10316,"startTime":1517847134817,"screenshots":[{"screenshot":"e6f7d4eae7def4b0d2e670bdd385412f881ff291119aa5799086582525a5eefa.png"}],"result":"SUCCESS","precondition":false},{"number":2,"description":"When insiro no campo de busca netShoes \"\u003cbusca\u003e\"","duration":12460,"startTime":1517847145136,"screenshots":[{"screenshot":"5f2fd36cab0e0357643c07b89ca7566ac7aa7c653deca54aa6987e7218d8f1a7.png"},{"screenshot":"2b43471002507e407cd4e31d5c6a80161f793c2638eed4dbd2f482b9e08613bc.png"}],"result":"SUCCESS","precondition":false},{"number":3,"description":"And seleciono opcao de outlet \"\u003copcao\u003e\"","duration":14082,"startTime":1517847157597,"screenshots":[{"screenshot":"1063651a85260d0b3d9738d859072e8726453d2834c6c956d6b5fe395b992c26.png"}],"result":"SUCCESS","precondition":false},{"number":4,"description":"And seleciono faixa de preco","duration":19927,"startTime":1517847171679,"screenshots":[{"screenshot":"d436bdee9d76d24f0e73fc16e8e448a83d5e5df602a8cea7b874ef89afd7ad38.png"}],"result":"SUCCESS","precondition":false},{"number":5,"description":"And seleciono o tenis \"\u003ctenis\u003e\"","duration":25215,"startTime":1517847191606,"screenshots":[{"screenshot":"442ce2185aa67480bd59890281a13f00a8d4172ccde9669322fa6e1c53cea8c1.png"}],"result":"SUCCESS","precondition":false},{"number":6,"description":"And seleciono o tamanho \"\u003ctam\u003e\"","duration":4386,"startTime":1517847216822,"screenshots":[{"screenshot":"a088f36efe94153fa1f8db5951025069355ed631ec11d8f0cf7ba5c994a5ed14.png"}],"result":"SUCCESS","precondition":false},{"number":7,"description":"And clico no botao \u0027 COMPRAR\u0027","duration":19424,"startTime":1517847221209,"screenshots":[{"screenshot":"eae19bf4acd358ce31644102392d02f70a0f9e34425ef206e1cd2f23120e2420.png"}],"result":"SUCCESS","precondition":false},{"number":8,"description":"Then verifico se o item foi adicionado ao carrinho netShoes \"\u003ctenis\u003e\"","duration":891,"startTime":1517847240634,"screenshots":[{"screenshot":"eae19bf4acd358ce31644102392d02f70a0f9e34425ef206e1cd2f23120e2420.png"}],"result":"SUCCESS","precondition":false}],"userStory":{"id":"escolher-um-calçado-na-seção-outlet-com-valor-abaixo-de-r$150,00","storyName":"Escolher um calçado na seção outlet com valor abaixo de R$150,00","path":"CT03-EscolherCalçadoNaSeçãoOutletComValorAbaixoR$150,00.feature","type":"feature"},"featureTag":{"name":"Escolher um calçado na seção outlet com valor abaixo de R$150,00","type":"feature"},"title":"Escolher um calçado na seção outlet com valor abaixo de R$150,00","description":"","tags":[{"name":"netShoes","type":"tag"},{"name":"Escolher um calçado na seção outlet com valor abaixo de R$150,00","type":"feature"}],"startTime":1517847134568,"duration":0,"projectKey":"","dataTable":{"headers":["url","busca","opcao","tenis","tam"],"rows":[{"values":["http://www.netshoes.com.br/","outlet","Tênis","Tênis Diadora Mission Masculino","41"],"result":"SUCCESS"}],"predefinedRows":true,"dataSetDescriptors":[{"startRow":0,"rowCount":0,"name":"","description":""}]},"manual":false,"result":"SUCCESS"}