{"name":"Buscar Agencia","id":"buscar-agencia-e-exibir-detalhes:Buscar Agencia","testSteps":[{"number":1,"description":"Given estou na pagina inicial \"\u003curl\u003e\"","duration":5724,"startTime":1519142685403,"screenshots":[{"screenshot":"4fb5ea263173c000484fe34ffcacd518e0936b9be0d4fba09f0a3dea31c44107.png"}],"result":"SUCCESS","precondition":false},{"number":2,"description":"When clico na opcao de servico \"\u003copcao\u003e\"","duration":3797,"startTime":1519142691128,"screenshots":[{"screenshot":"3b5396b43a84708ed9b5d90a484e11a21f269302c491168cc57b363cc8d7b751.png"},{"screenshot":"bbb52572cbe2ff0489683dabff54a6e982833eb494c3dd0a809e1154ab379c12.png"}],"result":"SUCCESS","precondition":false},{"number":3,"description":"And seleciono \u0027Busca_agencia_por\u0027 \"\u003cbuscaAgencia\u003e\"","duration":2975,"startTime":1519142694926,"screenshots":[{"screenshot":"581e37b3514e4f481b1c74333c2567b438575145777b044ca56294be61965577.png"},{"screenshot":"b8d6dabb985a6e7edd63e007a99a866469c5853f9789d58f51aab02f57592b2f.png"}],"result":"SUCCESS","precondition":false},{"number":4,"description":"And seleciono o \u0027Estado\u0027 \"\u003cestado\u003e\"","duration":957,"startTime":1519142697901,"screenshots":[{"screenshot":"ef10b7f1f57a97b7d386fa447d2fb06f8b9a0e156bd6e50460a62db93fd2dd36.png"}],"result":"SUCCESS","precondition":false},{"number":5,"description":"And seleciono o \u0027Municipio\u0027 \"\u003cmunicipio\u003e\"","duration":7826,"startTime":1519142698859,"screenshots":[{"screenshot":"f5ff080f0419ff957d45751bd1fca5c348a3b3af77620f03aa6a3fa24fa3b262.png"},{"screenshot":"da7626883c781d181281a27f36593e463a8ad648d70786f28cbf4ef59f430996.png"}],"result":"SUCCESS","precondition":false},{"number":6,"description":"And seleciono o \u0027Bairro\u0027 \"\u003cbairro\u003e\"","duration":5980,"startTime":1519142706686,"screenshots":[{"screenshot":"4ad8f749c7566fa8586ff82dc26fbc48607aca65da6b987473a1c4b080c4e118.png"},{"screenshot":"529c9d796c2a792be1ef2e86dd99b47c1ce6e607e0ee775e730e7f348007a9b2.png"}],"result":"SUCCESS","precondition":false},{"number":7,"description":"Then seleciono a agencia \"\u003cagencia\u003e\"","duration":6162,"startTime":1519142712666,"screenshots":[{"screenshot":"02df7c553b093647157cdc07a0b49eaa6e99bf29b4ec663dff0552f0a3a00f08.png"}],"result":"SUCCESS","precondition":false}],"userStory":{"id":"buscar-agencia-e-exibir-detalhes","storyName":"Buscar Agencia e exibir detalhes","path":"CT03-BuscarAgenciaEExibirDetalhes.feature","type":"feature"},"featureTag":{"name":"Buscar Agencia e exibir detalhes","type":"feature"},"title":"Buscar Agencia","description":"","tags":[{"name":"Buscar Agencia e exibir detalhes","type":"feature"},{"name":"Correios","type":"tag"}],"startTime":1519142685403,"duration":0,"projectKey":"","dataTable":{"headers":["url","opcao","buscaAgencia","estado","municipio","bairro","agencia"],"rows":[{"values":["http://www.correios.com.br/para-voce","Rede de Atendimento","Localidade","SÃO PAULO","SAO PAULO","CENTRO","AGF BOA VISTA"],"result":"SUCCESS"}],"predefinedRows":true,"dataSetDescriptors":[{"startRow":0,"rowCount":0,"name":"","description":""}]},"manual":false,"result":"SUCCESS"}